tqdm_rich_logger/__init__.py
tqdm_rich_logger/tqdm_rich_logger.py
tqdm_rich_logger-0.3.0.dist-info/licenses/LICENSE
tqdm_rich_logger-0.3.0.dist-info/METADATA
tqdm_rich_logger-0.3.0.dist-info/WHEEL
tqdm_rich_logger-0.3.0.dist-info/top_level.txt
tqdm_rich_logger-0.3.0.dist-info/RECORD
