Metadata-Version: 2.4
Name: tqdm-rich-logger
Version: 0.3.0
Summary: TQDM-safe Rich logger with file output and exception catching
Home-page: https://github.com/madhavarora03/tqdm-rich-logger
Author: Madhav Arora
Author-email: your.email@example.com
Classifier: Programming Language :: Python :: 3
Classifier: License :: OSI Approved :: MIT License
Classifier: Operating System :: OS Independent
Requires-Python: >=3.7
License-File: LICENSE
Requires-Dist: rich>=13.0.0
Requires-Dist: tqdm>=4.0.0
Dynamic: author
Dynamic: author-email
Dynamic: classifier
Dynamic: description
Dynamic: description-content-type
Dynamic: home-page
Dynamic: license-file
Dynamic: requires-dist
Dynamic: requires-python
Dynamic: summary
